ckanext/__init__.py
ckanext/let_me_in/__init__.py
ckanext/let_me_in/cli.py
ckanext/let_me_in/config.py
ckanext/let_me_in/config_declaration.yaml
ckanext/let_me_in/interfaces.py
ckanext/let_me_in/plugin.py
ckanext/let_me_in/utils.py
ckanext/let_me_in/views.py
ckanext/let_me_in/logic/action.py
ckanext/let_me_in/logic/auth.py
ckanext/let_me_in/logic/schema.py
ckanext/let_me_in/logic/validators.py
ckanext/let_me_in/tests/__init__.py
ckanext/let_me_in/tests/conftest.py
ckanext/let_me_in/tests/test_auth.py
ckanext/let_me_in/tests/test_config.py
ckanext/let_me_in/tests/test_interface.py
ckanext/let_me_in/tests/test_logic.py
ckanext/let_me_in/tests/test_validators.py
ckanext/let_me_in/tests/test_views.py
ckanext/let_me_in_impostor/__init__.py
ckanext/let_me_in_impostor/helpers.py
ckanext/let_me_in_impostor/model.py
ckanext/let_me_in_impostor/plugin.py
ckanext/let_me_in_impostor/views.py
ckanext/let_me_in_impostor/migration/let_me_in_impostor/env.py
ckanext/let_me_in_impostor/migration/let_me_in_impostor/versions/c27704201743_add_lmi_impostor_session_table.py
ckanext/let_me_in_impostor/tests/__init__.py
ckanext/let_me_in_impostor/tests/conftest.py
ckanext/let_me_in_impostor/tests/test_config.py
ckanext/let_me_in_impostor/tests/test_model.py
ckanext/let_me_in_impostor/tests/test_views.py
ckanext_let_me_in-1.1.3.dist-info/licenses/LICENSE
ckanext_let_me_in-1.1.3.dist-info/METADATA
ckanext_let_me_in-1.1.3.dist-info/WHEEL
ckanext_let_me_in-1.1.3.dist-info/entry_points.txt
ckanext_let_me_in-1.1.3.dist-info/top_level.txt
ckanext_let_me_in-1.1.3.dist-info/RECORD
